pyEulerCurves/__init__.py
pyEulerCurves/_compute_local_EC_VR.cpython-313-darwin.so
pyEulerCurves/_compute_local_EC_cubical.cpython-313-darwin.so
pyEulerCurves/_template.py
pyEulerCurves/_version.py
pyEulerCurves/distance_utils.py
pyEulerCurves/ecc_cubical.py
pyEulerCurves/ecc_pointcloud.py
pyEulerCurves/ecc_utils.py
pyEulerCurves/src/Bitmap_cubical_complex.h
pyEulerCurves/src/Bitmap_cubical_complex_periodic_boundary_conditions.h
pyEulerCurves/src/compute_local_EC_VR.cpp
pyEulerCurves/src/compute_local_EC_cubical.cpp
pyEulerCurves/src/counter.h
pyeulercurves-0.5.post0.dist-info/licenses/LICENSE
pyeulercurves-0.5.post0.dist-info/METADATA
pyeulercurves-0.5.post0.dist-info/WHEEL
pyeulercurves-0.5.post0.dist-info/top_level.txt
pyeulercurves-0.5.post0.dist-info/RECORD
