Metadata-Version: 2.4
Name: pyEulerCurves
Version: 0.5.post0
Summary: A python package to compute Euler Characteristic Curves
Home-page: https://github.com/dgurnari/pyEulerCurves
Author: Davide Gurnari
Author-email: davide.gurnari@gmail.com
Requires-Python: >=3.7
License-File: LICENSE
Requires-Dist: numpy
Requires-Dist: matplotlib
Requires-Dist: scikit-learn
Requires-Dist: pybind11>=2.10.0
Requires-Dist: gudhi
Requires-Dist: numba
Dynamic: author
Dynamic: author-email
Dynamic: home-page
Dynamic: license-file
Dynamic: requires-dist
Dynamic: requires-python
Dynamic: summary
